gnome_extension_uploader/__init__.py
gnome_extension_uploader/cli.py
gnome_extension_uploader/utils.py
gnome_extension_uploader-0.1.6.dist-info/entry_points.txt
gnome_extension_uploader-0.1.6.dist-info/WHEEL
gnome_extension_uploader-0.1.6.dist-info/METADATA
gnome_extension_uploader-0.1.6.dist-info/RECORD
