Metadata-Version: 2.1
Name: gnome-extension-uploader
Version: 0.1.6
Summary: 
Home-page: https://github.com/SebastianLuebke/gnome-extension-uploader
Author: Sebastian Noel Lübke
Author-email: sebastian@luebke.io
Requires-Python: >=3.8,<4.0
Classifier: Programming Language :: Python :: 3
Classifier: Programming Language :: Python :: 3.8
Classifier: Programming Language :: Python :: 3.9
Requires-Dist: requests (>=2.24.0,<3.0.0)
Requires-Dist: typer (>=0.3.2,<0.4.0)
Project-URL: Repository, https://github.com/SebastianLuebke/gnome-extension-uploader
